perceptron_pkg/__init__.py
perceptron_pkg/perceptron.py
perceptron_prasath-0.0.3.dist-info/METADATA
perceptron_prasath-0.0.3.dist-info/WHEEL
perceptron_prasath-0.0.3.dist-info/licenses/LICENSE
perceptron_prasath-0.0.3.dist-info/RECORD
