Metadata-Version: 2.4
Name: perceptron-prasath
Version: 0.0.3
Summary: A small package for perceptron
Project-URL: Homepage, https://github.com/prasath/perceptron_pkg
Project-URL: Issues, https://github.com/prasath/perceptron_pkg/issues
Author-email: prasath <prasathks20@gmail.com>
License: MIT
License-File: LICENSE
Classifier: License :: OSI Approved :: MIT License
Classifier: Operating System :: OS Independent
Classifier: Programming Language :: Python :: 3
Requires-Python: >=3.6
Requires-Dist: joblib
Requires-Dist: numpy
Requires-Dist: pandas
